gradio_flatpickr_calendar/__init__.py
gradio_flatpickr_calendar/calendar.py
gradio_flatpickr_calendar/calendar.pyi
gradio_flatpickr_calendar/templates/component/Index-Dxzk1Xy0.js
gradio_flatpickr_calendar/templates/component/_basePickBy-CG7czl1c.js
gradio_flatpickr_calendar/templates/component/_baseUniq-DVtHBapI.js
gradio_flatpickr_calendar/templates/component/arc-B-8POkFg.js
gradio_flatpickr_calendar/templates/component/architectureDiagram-VXUJARFQ-2GNQaRbI.js
gradio_flatpickr_calendar/templates/component/auto-render-BwaQGe8P.js
gradio_flatpickr_calendar/templates/component/blockDiagram-VD42YOAC-CD3bvFgH.js
gradio_flatpickr_calendar/templates/component/c4Diagram-YG6GDRKO-CR2338gf.js
gradio_flatpickr_calendar/templates/component/channel-Cr4z7U_W.js
gradio_flatpickr_calendar/templates/component/chunk-4BX2VUAB-BmTMa99_.js
gradio_flatpickr_calendar/templates/component/chunk-55IACEB6-DgaLLoxd.js
gradio_flatpickr_calendar/templates/component/chunk-B4BG7PRW-iDNX4c8P.js
gradio_flatpickr_calendar/templates/component/chunk-DI55MBZ5-Cw6Nwu7w.js
gradio_flatpickr_calendar/templates/component/chunk-FMBD7UC4-x9XDbGMJ.js
gradio_flatpickr_calendar/templates/component/chunk-QN33PNHL-zJJwfwLr.js
gradio_flatpickr_calendar/templates/component/chunk-QZHKN3VN-DbzDsHz2.js
gradio_flatpickr_calendar/templates/component/chunk-TZMSLE5B-BbuKi8C-.js
gradio_flatpickr_calendar/templates/component/classDiagram-2ON5EDUG-D839WiJy.js
gradio_flatpickr_calendar/templates/component/classDiagram-v2-WZHVMYZB-D839WiJy.js
gradio_flatpickr_calendar/templates/component/clone-IDr4dBRf.js
gradio_flatpickr_calendar/templates/component/cose-bilkent-S5V4N54A-e0U0YOJB.js
gradio_flatpickr_calendar/templates/component/cytoscape.esm-ZmItrg9y.js
gradio_flatpickr_calendar/templates/component/dagre-6UL2VRFP-hgO0W6ya.js
gradio_flatpickr_calendar/templates/component/defaultLocale-D7EN2tov.js
gradio_flatpickr_calendar/templates/component/diagram-PSM6KHXK-DFICoa_8.js
gradio_flatpickr_calendar-0.0.6.dist-info/METADATA
gradio_flatpickr_calendar-0.0.6.dist-info/WHEEL
gradio_flatpickr_calendar-0.0.6.dist-info/licenses/LICENSE
gradio_flatpickr_calendar-0.0.6.dist-info/RECORD
