Metadata-Version: 2.4
Name: gradio_flatpickr_calendar
Version: 0.0.6
Summary: Gradio component for selecting dates or ranges of dates with a Flatpickr calendar 📆
Project-URL: repository, https://github.com/Florian-BACHO/gradio-flatpickr-calendar
Author-email: Florian Bacho <f.bacho@outlook.fr>
License-Expression: MIT
License-File: LICENSE
Keywords: calendar,forms,gradio-custom-component,gradio-template-Fallback,time
Classifier: Development Status :: 3 - Alpha
Classifier: License :: OSI Approved :: Apache Software License
Classifier: Operating System :: OS Independent
Classifier: Programming Language :: Python :: 3
Classifier: Programming Language :: Python :: 3 :: Only
Classifier: Programming Language :: Python :: 3.8
Classifier: Programming Language :: Python :: 3.9
Classifier: Programming Language :: Python :: 3.10
Classifier: Programming Language :: Python :: 3.11
Classifier: Topic :: Scientific/Engineering
Classifier: Topic :: Scientific/Engineering :: Artificial Intelligence
Classifier: Topic :: Scientific/Engineering :: Visualization
Requires-Python: >=3.8
Requires-Dist: gradio>=4.0
Provides-Extra: dev
Requires-Dist: build; extra == 'dev'
Requires-Dist: twine; extra == 'dev'
